{
	"GlobalData": {
		"sysAdminEmail": "ravi.middha@highq.com",
		"sysAdminPassword": "Password@123",
		"OrgData": {
			"Organization 1": {
				"name": "dashboard210.com",
				"Internal": true,
				"users": [
					"dashboard.normaluser2102"
				]
			}
		},
		"userResetData": {
			"defaultPassword": "Password@123",
			"userResetPasswordData": {
				"Organization 1": {
					"name": "dashboard210.com",
					"user 1": {
						"id": "dashboard.normaluser2102",
						"newPassword": "Password@123"
					}
				}
			},
			"userStatus": "Active",
			"isStatusLocked": false
		},
		"PreConfiguration": {
			"PreConfiguration 1": [
				"setOrg",
				"addSystemAdminUsers",
				"createSite",
				"setGroupPermission",
				"enableModules",
				"addsiteuserswithoutroles",
				"setSiteUserRoles"
			],
			"Sites": {
				"name": "Dashboard_TC0210_2"
			},
			"SiteGroupPermission": false,
			"modules": [
				"All"
			],
			"siteUsers": [
				"above all"
			],
			"Users": {
				"user1": {
					"id": "dashboard.normaluser2102@dashboard210.com",
					"Permissions": {
						"Modules": {
							"All": {
								"View": true,
								"Edit": true
							}
						},
						"Files": {
							
						},
						"AdminGroups": {
							
						}
					}
				}
			}
		}
	}
}